{
  "internalId": "ARROW",
  "name": "Flint Arrow",
  "category": "Arrow",
  "source": "HypixelAPI",
  "npcValue": 2,
  "lore": "&7Damage: &c+1\n\n&8Stats added when shot!\n&f&lCOMMON ARROW&r",
  "flags": {
    "tradable": true,
    "bazaarable": false,
    "auctionable": true,
    "reforgeable": false,
    "enchantable": false,
    "museumable": false,
    "soulboundable": false,
    "sackable": false
  },
  "data": {
    "id": "ARROW",
    "material": "ARROW",
    "name": "Flint Arrow",
    "category": "ARROW",
    "npc_sell_price": 2,
    "stats": {
      "DAMAGE": 1
    }
  },
  "recipes": [],
  "soldBy": [
    {
      "id": "NPC_GREGORY",
      "name": "Gregory",
      "cost": [
        {
          "type": "COINS",
          "amount": 240
        }
      ],
      "amount": 20
    },
    {
      "id": "NPC_OPHELIA",
      "name": "Ophelia",
      "cost": [
        {
          "type": "COINS",
          "amount": 200
        }
      ],
      "amount": 20
    },
    {
      "id": "NPC_WEAPONSMITH_MERCHANT",
      "name": "Weaponsmith",
      "cost": [
        {
          "type": "COINS",
          "amount": 40
        }
      ]
    }
  ]
}