{
  "internalId": "DAEDALUS_STICK",
  "name": "Daedalus Stick",
  "category": "Item",
  "source": "HypixelAPI",
  "npcValue": 250000,
  "lore": "&7Drops rarely off of Minotaurs from\n&7Diana's Mythological Ritual.\n\n&eRight-click to view recipes!\n\n&6&lLEGENDARY&r",
  "flags": {
    "tradable": false,
    "bazaarable": false,
    "auctionable": false,
    "reforgeable": false,
    "enchantable": false,
    "museumable": false,
    "soulboundable": false,
    "sackable": false
  },
  "data": {
    "id": "DAEDALUS_STICK",
    "material": "STICK",
    "name": "Daedalus Stick",
    "tier": "LEGENDARY",
    "glowing": true,
    "npc_sell_price": 250000,
    "has_uuid": true
  },
  "recipes": []
}