{
  "internalId": "ENCHANTMENT_TURBO_CACTUS_4",
  "name": "Turbo-Cacti IV",
  "category": null,
  "source": "HypixelWikiEnchantment",
  "npcValue": 0,
  "lore": "&7&9Turbo-Cacti IV\n&7Grants &6+20☘ Cactus Fortune&7.\n&7Requires &cBronze &7in a &aCactus Contest&7!\n\n&7Applicable on: &9Axe&7, &9Hoe\n&7Apply Cost: &340 Exp Levels\n\n&7Use this on an item in an Anvil to\n&7apply it!\n\n&f&lCOMMON&r",
  "flags": {
    "tradable": false,
    "bazaarable": true,
    "auctionable": false,
    "reforgeable": false,
    "enchantable": false,
    "museumable": false,
    "soulboundable": false,
    "sackable": false
  },
  "data": null,
  "recipes": []
}