{
  "internalId": "ENCHANTED_HUGE_MUSHROOM_2",
  "name": "Enchanted Red Mushroom Block",
  "category": "Item",
  "source": "HypixelAPI",
  "npcValue": 256000,
  "lore": "&7&8Collection Item\n\n&9&lRARE&r",
  "flags": {
    "tradable": true,
    "bazaarable": true,
    "auctionable": false,
    "reforgeable": false,
    "enchantable": false,
    "museumable": false,
    "soulboundable": false,
    "sackable": false
  },
  "data": {
    "id": "ENCHANTED_HUGE_MUSHROOM_2",
    "material": "HUGE_MUSHROOM_2",
    "name": "Enchanted Red Mushroom Block",
    "tier": "RARE",
    "glowing": true,
    "npc_sell_price": 256000
  },
  "recipes": [
    {
      "name": "first",
      "type": "crafting",
      "resultId": "ENCHANTED_HUGE_MUSHROOM_2",
      "resultQuantity": 1,
      "crafting": {
        "1": {
          "itemId": "ENCHANTED_RED_MUSHROOM",
          "quantity": 8
        },
        "2": {
          "itemId": "ENCHANTED_RED_MUSHROOM",
          "quantity": 8
        },
        "4": {
          "itemId": "ENCHANTED_RED_MUSHROOM",
          "quantity": 8
        },
        "5": {
          "itemId": "ENCHANTED_RED_MUSHROOM",
          "quantity": 8
        }
      }
    },
    {
      "name": "second",
      "type": "crafting",
      "resultId": "ENCHANTED_HUGE_MUSHROOM_2",
      "resultQuantity": 1,
      "crafting": {
        "1": {
          "itemId": "HUGE_MUSHROOM_2",
          "quantity": 64
        },
        "2": {
          "itemId": "HUGE_MUSHROOM_2",
          "quantity": 64
        },
        "3": {
          "itemId": "HUGE_MUSHROOM_2",
          "quantity": 64
        },
        "4": {
          "itemId": "HUGE_MUSHROOM_2",
          "quantity": 64
        },
        "5": {
          "itemId": "HUGE_MUSHROOM_2",
          "quantity": 64
        },
        "6": {
          "itemId": "HUGE_MUSHROOM_2",
          "quantity": 64
        },
        "7": {
          "itemId": "HUGE_MUSHROOM_2",
          "quantity": 64
        },
        "8": {
          "itemId": "HUGE_MUSHROOM_2",
          "quantity": 64
        },
        "9": {
          "itemId": "HUGE_MUSHROOM_2",
          "quantity": 64
        }
      }
    }
  ]
}