{
  "internalId": "ENCHANTED_WOOL",
  "name": "Enchanted Wool",
  "category": "Item",
  "source": "HypixelAPI",
  "npcValue": 320,
  "lore": "&7&8Collection Item\n\n&a&lUNCOMMON&r",
  "flags": {
    "tradable": false,
    "bazaarable": false,
    "auctionable": false,
    "reforgeable": false,
    "enchantable": false,
    "museumable": false,
    "soulboundable": false,
    "sackable": false
  },
  "data": {
    "id": "ENCHANTED_WOOL",
    "material": "WOOL",
    "name": "Enchanted Wool",
    "tier": "UNCOMMON",
    "glowing": true,
    "npc_sell_price": 320
  },
  "recipes": [
    {
      "name": "first",
      "type": "crafting",
      "resultId": "ENCHANTED_WOOL",
      "resultQuantity": 1,
      "crafting": {
        "2": {
          "itemId": "WOOL",
          "quantity": 32
        },
        "4": {
          "itemId": "WOOL",
          "quantity": 32
        },
        "5": {
          "itemId": "WOOL",
          "quantity": 32
        },
        "6": {
          "itemId": "WOOL",
          "quantity": 32
        },
        "8": {
          "itemId": "WOOL",
          "quantity": 32
        }
      }
    },
    {
      "name": "second",
      "type": "crafting",
      "resultId": "ENCHANTED_WOOL",
      "resultQuantity": 1,
      "crafting": {
        "1": {
          "itemId": "WOOL",
          "quantity": 32
        },
        "2": {
          "itemId": "WOOL",
          "quantity": 32
        },
        "3": {
          "itemId": "WOOL",
          "quantity": 32
        },
        "4": {
          "itemId": "WOOL",
          "quantity": 32
        },
        "5": {
          "itemId": "WOOL",
          "quantity": 32
        }
      }
    }
  ]
}