{
  "internalId": "ENCHANTMENT_FEATHER_FALLING_20",
  "name": "Enchantment Feather Falling 20",
  "category": null,
  "source": "HypixelBazaar",
  "npcValue": 0,
  "lore": "",
  "flags": {
    "tradable": false,
    "bazaarable": true,
    "auctionable": false,
    "reforgeable": false,
    "enchantable": false,
    "museumable": false,
    "soulboundable": false,
    "sackable": false
  },
  "data": {
    "id": "ENCHANTMENT_FEATHER_FALLING_20",
    "name": "Enchantment Feather Falling 20"
  },
  "recipes": []
}