{
  "internalId": "GOLDEN_CARROT",
  "name": "Golden Carrot",
  "category": "Item",
  "source": "HypixelAPI",
  "npcValue": 4,
  "lore": "&7&8Brewing Ingredient\n\n&f&lCOMMON&r",
  "flags": {
    "tradable": true,
    "bazaarable": false,
    "auctionable": true,
    "reforgeable": false,
    "enchantable": false,
    "museumable": false,
    "soulboundable": false,
    "sackable": false
  },
  "data": {
    "id": "GOLDEN_CARROT",
    "material": "GOLDEN_CARROT",
    "name": "Golden Carrot",
    "npc_sell_price": 4
  },
  "recipes": []
}