{
  "internalId": "PERFECT_HELMET_9",
  "name": "Perfect Helmet - Tier IX",
  "category": "Helmet",
  "source": "HypixelAPI",
  "npcValue": 3788800,
  "lore": "&7Defense: &a+270\n&7 &8[&7❈&8] &8[&7❈&8] &8[&7❈&8]\n\n&eRight-click to view recipes!\n\n&7&8This item can be reforged!\n&6&lLEGENDARY HELMET&r",
  "flags": {
    "tradable": false,
    "bazaarable": false,
    "auctionable": false,
    "reforgeable": false,
    "enchantable": false,
    "museumable": false,
    "soulboundable": false,
    "sackable": false
  },
  "data": {
    "id": "PERFECT_HELMET_9",
    "material": "DIAMOND_HELMET",
    "name": "Perfect Helmet - Tier IX",
    "category": "HELMET",
    "tier": "LEGENDARY",
    "npc_sell_price": 3788800,
    "gemstone_slots": [
      {
        "slot_type": "AMETHYST",
        "costs": []
      },
      {
        "slot_type": "AMETHYST",
        "costs": []
      },
      {
        "slot_type": "AMETHYST",
        "costs": []
      }
    ],
    "stats": {
      "DEFENSE": 270
    },
    "dungeon_item_conversion_cost": {
      "essence_type": "DIAMOND",
      "amount": 40
    },
    "upgrade_costs": [
      [
        {
          "type": "ESSENCE",
          "essence_type": "DIAMOND",
          "amount": 20
        }
      ],
      [
        {
          "type": "ESSENCE",
          "essence_type": "DIAMOND",
          "amount": 30
        }
      ],
      [
        {
          "type": "ESSENCE",
          "essence_type": "DIAMOND",
          "amount": 50
        }
      ],
      [
        {
          "type": "ESSENCE",
          "essence_type": "DIAMOND",
          "amount": 100
        }
      ],
      [
        {
          "type": "ESSENCE",
          "essence_type": "DIAMOND",
          "amount": 150
        }
      ]
    ],
    "catacombs_requirements": [
      {
        "type": "DUNGEON_SKILL",
        "dungeon_type": "CATACOMBS",
        "level": 17
      }
    ]
  },
  "recipes": [
    {
      "name": "first",
      "type": "crafting",
      "resultId": "PERFECT_HELMET_9",
      "resultQuantity": 1,
      "crafting": {
        "2": {
          "itemId": "ENCHANTED_DIAMOND_BLOCK",
          "quantity": 1
        },
        "4": {
          "itemId": "ENCHANTED_DIAMOND_BLOCK",
          "quantity": 1
        },
        "5": {
          "itemId": "PERFECT_HELMET_8",
          "quantity": 1
        },
        "6": {
          "itemId": "ENCHANTED_DIAMOND_BLOCK",
          "quantity": 1
        },
        "8": {
          "itemId": "ENCHANTED_DIAMOND_BLOCK",
          "quantity": 1
        }
      }
    }
  ]
}