{
  "internalId": "SCORPION_FOIL",
  "name": "Scorpion Foil",
  "category": null,
  "source": "HypixelAPI",
  "npcValue": 0,
  "lore": "&7Damage: &c+120\n\n&7Strength: &c+60\n\n&7Crit Damage: &9+30%\n\n&7 &8[&7⚔&8]\n\n\n\n&7Deal &c+250% ❁ Damage&7 to and gain\n\n&3+30☯ Combat Wisdom &7against &4Ж\n\n&4Arthropod &7mobs.\n\n\n\n&6Ability: Webcutter \n\n&7This weapon can be used to clear\n\n&7webs left by the &4Tarantula\n\n&4Broodfather&7!\n\n\n\n&8This item can be reforged!\n\n&5&lEPIC SWORD&r",
  "flags": {
    "tradable": true,
    "bazaarable": false,
    "auctionable": true,
    "reforgeable": true,
    "enchantable": true,
    "museumable": true,
    "soulboundable": false,
    "sackable": false
  },
  "data": {
    "id": "SCORPION_FOIL",
    "material": "WOOD_SWORD",
    "name": "Scorpion Foil",
    "category": "SWORD",
    "tier": "EPIC",
    "gemstone_slots": [
      {
        "slot_type": "COMBAT",
        "costs": []
      }
    ],
    "requirements": [
      {
        "type": "SLAYER",
        "level": 6,
        "slayer_boss_type": "spider"
      }
    ],
    "museum_data": {
      "donation_xp": 7,
      "parent": {
        "SCORPION_FOIL": "STING"
      },
      "type": "WEAPONS",
      "game_stage": "SKILLED",
      "mapped_item_ids": []
    },
    "stats": {
      "DAMAGE": 120,
      "STRENGTH": 60,
      "CRITICAL_DAMAGE": 30
    },
    "dungeon_item_conversion_cost": {
      "essence_type": "SPIDER",
      "amount": 100
    },
    "upgrade_costs": [
      [
        {
          "type": "ESSENCE",
          "essence_type": "SPIDER",
          "amount": 50
        }
      ],
      [
        {
          "type": "ESSENCE",
          "essence_type": "SPIDER",
          "amount": 100
        }
      ],
      [
        {
          "type": "ESSENCE",
          "essence_type": "SPIDER",
          "amount": 150
        }
      ],
      [
        {
          "type": "ESSENCE",
          "essence_type": "SPIDER",
          "amount": 200
        }
      ],
      [
        {
          "type": "ESSENCE",
          "essence_type": "SPIDER",
          "amount": 250
        }
      ]
    ]
  },
  "recipes": [
    {
      "name": "first",
      "type": "crafting",
      "resultId": "SCORPION_FOIL",
      "resultQuantity": 1,
      "crafting": {
        "1": {
          "itemId": "TARANTULA_SILK",
          "quantity": 4
        },
        "2": {
          "itemId": "ENCHANTED_ACACIA_LOG",
          "quantity": 64
        },
        "3": {
          "itemId": "TARANTULA_SILK",
          "quantity": 4
        },
        "4": {
          "itemId": "TARANTULA_SILK",
          "quantity": 4
        },
        "5": {
          "itemId": "ENCHANTED_ACACIA_LOG",
          "quantity": 64
        },
        "6": {
          "itemId": "TARANTULA_SILK",
          "quantity": 4
        },
        "7": {
          "itemId": "TARANTULA_SILK",
          "quantity": 4
        },
        "8": {
          "itemId": "STICK",
          "quantity": 1
        },
        "9": {
          "itemId": "TARANTULA_SILK",
          "quantity": 4
        }
      }
    }
  ]
}