{
  "internalId": "SNOW_SHOVEL",
  "name": "Snow Shovel",
  "category": "Item",
  "source": "HypixelAPI",
  "npcValue": 0,
  "lore": "\n&6Ability: Snow Placer  &e&lRIGHT CLICK&r\n&7Right-Click a block to place a 3x3\n&7snow layer.\n\n&7Cost: &610 Coins\n\n&9&lRARE&r",
  "flags": {
    "tradable": true,
    "bazaarable": false,
    "auctionable": true,
    "reforgeable": false,
    "enchantable": false,
    "museumable": false,
    "soulboundable": false,
    "sackable": false
  },
  "data": {
    "id": "SNOW_SHOVEL",
    "material": "DIAMOND_SPADE",
    "name": "Snow Shovel",
    "tier": "RARE"
  },
  "recipes": [],
  "soldBy": [
    {
      "id": "NPC_SCOOP",
      "name": "Scoop",
      "cost": [
        {
          "type": "COINS",
          "amount": 2500
        }
      ],
      "amount": 0
    }
  ]
}