{
  "internalId": "THORNLEAF_SCYTHE",
  "name": "Thornleaf Scythe",
  "category": null,
  "source": "HypixelAPI",
  "npcValue": 50,
  "lore": "&7A crudely sharpened implement used\n&7by the &cBarbarians &7to harvest &aRed\n&aThornleaf&7.\n\n&7&8This item can be reforged!\n&a&lUNCOMMON HOE&r",
  "flags": {
    "tradable": true,
    "bazaarable": false,
    "auctionable": true,
    "reforgeable": true,
    "enchantable": true,
    "museumable": false,
    "soulboundable": false,
    "sackable": false
  },
  "data": {
    "id": "THORNLEAF_SCYTHE",
    "material": "IRON_HOE",
    "name": "Thornleaf Scythe",
    "category": "HOE",
    "tier": "UNCOMMON",
    "glowing": true,
    "npc_sell_price": 50
  },
  "recipes": []
}