{
  "internalId": "NPC_DANTE",
  "name": "Mayor Dante",
  "source": "HypixelWiki",
  "slots": {
    "a1": {
      "material": "black_stained_glass_pane",
      "lore": ""
    },
    "a2": {
      "material": "black_stained_glass_pane",
      "lore": ""
    },
    "a3": {
      "material": "black_stained_glass_pane",
      "lore": ""
    },
    "a4": {
      "material": "black_stained_glass_pane",
      "lore": ""
    },
    "a5": {
      "material": "black_stained_glass_pane",
      "lore": ""
    },
    "a6": {
      "material": "black_stained_glass_pane",
      "lore": ""
    },
    "a7": {
      "material": "black_stained_glass_pane",
      "lore": ""
    },
    "a8": {
      "material": "black_stained_glass_pane",
      "lore": ""
    },
    "a9": {
      "material": "black_stained_glass_pane",
      "lore": ""
    },
    "b1": {
      "material": "black_stained_glass_pane",
      "lore": ""
    },
    "b2": {
      "material": "black_stained_glass_pane",
      "lore": ""
    },
    "b3": {
      "material": "mayor_dante",
      "name": "Mayor Dante",
      "lore": "&8Changes List\n\n&9Economy Restoration\n&7 - Double AH & Bazaar Tax\n&7- 10% coin tax on shops\n&7- 10 coins per minute for chatting\n&7- 2 coin toll on travelling\n&7between islands\n\n&6Increased Security\n&7- Hired Goons to protect\n&7official buildings\n&7- Cancelled hazardous events\n&7- Decreased sunlight, prevent sunburn"
    },
    "b4": {
      "material": "jukebox",
      "name": "&bMayor Election Results",
      "lore": "&8Year 128\n\n&c100.0%&8 ○ &eall votes&8 <nowiki>"
    },
    "b5": {
      "material": "black_stained_glass_pane",
      "lore": ""
    },
    "b6": {
      "lore": "Happy Mask\n&7Wear this mask to show your support\n&7for Dante.\n\n&7&8This item can be reforged!\n&a&lUNCOMMON HELMET&r\n\n&7Cost\n&6 100 Coins",
      "cost": [
        {
          "type": "COINS",
          "amount": 100
        }
      ],
      "output": [
        {
          "type": "ITEM",
          "item_id": "HAPPY_MASK"
        }
      ]
    },
    "b7": {
      "lore": "Dante Talisman\n&7Official medal proving your eternal\n&7support for Dante.\n\n&7Can be shown to goons in place of a\n&7Happy Mask for entry into official\n&7buildings.\n\n&f&lCOMMON ACCESSORY&r\n\n&7Cost\n&6 1,000,000 Coins",
      "cost": [
        {
          "type": "COINS",
          "amount": 1000000
        }
      ],
      "output": [
        {
          "type": "ITEM",
          "item_id": "DANTE_TALISMAN"
        }
      ]
    },
    "b8": {
      "material": "black_stained_glass_pane",
      "lore": ""
    },
    "b9": {
      "material": "black_stained_glass_pane",
      "lore": ""
    },
    "c1": {
      "material": "black_stained_glass_pane",
      "lore": ""
    },
    "c2": {
      "material": "black_stained_glass_pane",
      "lore": ""
    },
    "c3": {
      "material": "black_stained_glass_pane",
      "lore": ""
    },
    "c4": {
      "material": "black_stained_glass_pane",
      "lore": ""
    },
    "c5": {
      "material": "black_stained_glass_pane",
      "lore": ""
    },
    "c6": {
      "material": "black_stained_glass_pane",
      "lore": ""
    },
    "c7": {
      "material": "black_stained_glass_pane",
      "lore": ""
    },
    "c8": {
      "material": "black_stained_glass_pane",
      "lore": ""
    },
    "c9": {
      "material": "black_stained_glass_pane",
      "lore": ""
    },
    "d1": {
      "material": "black_stained_glass_pane",
      "lore": ""
    },
    "d2": {
      "material": "black_stained_glass_pane",
      "lore": ""
    },
    "d3": {
      "material": "black_stained_glass_pane",
      "lore": ""
    },
    "d4": {
      "material": "black_stained_glass_pane",
      "lore": ""
    },
    "d5": {
      "material": "barrier",
      "lore": ""
    },
    "d6": {
      "material": "black_stained_glass_pane",
      "lore": ""
    },
    "d7": {
      "material": "black_stained_glass_pane",
      "lore": ""
    },
    "d8": {
      "material": "black_stained_glass_pane",
      "lore": ""
    },
    "d9": {
      "material": "black_stained_glass_pane",
      "lore": ""
    }
  },
  "rows": "4"
}